ndexbiogridloader/__init__.py
ndexbiogridloader/chem_load_plan.json
ndexbiogridloader/chemical_style.cx
ndexbiogridloader/chemicals_list.txt
ndexbiogridloader/exceptions.py
ndexbiogridloader/ndexloadbiogrid.py
ndexbiogridloader/organism_list.txt
ndexbiogridloader/organism_load_plan.json
ndexbiogridloader/organism_style.cx
ndexbiogridloader-1.0.0.data/scripts/ndexloadbiogrid.py
ndexbiogridloader-1.0.0.dist-info/AUTHORS.rst
ndexbiogridloader-1.0.0.dist-info/LICENSE
ndexbiogridloader-1.0.0.dist-info/METADATA
ndexbiogridloader-1.0.0.dist-info/WHEEL
ndexbiogridloader-1.0.0.dist-info/top_level.txt
ndexbiogridloader-1.0.0.dist-info/RECORD
