Metadata-Version: 2.1
Name: ndexbiogridloader
Version: 1.0.0
Summary: Loads BioGRID data into NDEx
Home-page: https://github.com/ndexcontent/ndexbiogridloader
Author: Vladimir Rynkov
Author-email: vrynkov@yahoo.edu
License: BSD license
Keywords: ndexbiogridloader
Platform: UNKNOWN
Classifier: Development Status :: 2 - Pre-Alpha
Classifier: Intended Audience :: Developers
Classifier: License :: OSI Approved :: BSD License
Classifier: Natural Language :: English
Classifier: Programming Language :: Python :: 3.6
Classifier: Programming Language :: Python :: 3.7
Requires-Dist: ndex2 (<4.0.0,>=3.1.0a1)
Requires-Dist: ndexutil (<1.0.0,>=0.1.0a3)
Requires-Dist: requests
Requires-Dist: pandas
Requires-Dist: networkx
Requires-Dist: scipy
Requires-Dist: tqdm
Requires-Dist: py4cytoscape
